Metadata-Version: 2.4
Name: adafruit-circuitpython-displayio-sh1106
Version: 2.0.2
Summary: DisplayIO compatible library for SH1106 OLED displays
Author-email: Adafruit Industries <circuitpython@adafruit.com>
License: MIT
Project-URL: Homepage, https://github.com/adafruit/Adafruit_CircuitPython_DisplayIO_SH1106.git
Keywords: adafruit,blinka,circuitpython,micropython,displayio_sh1106,displayio,oled,sh1106,display
Classifier: Intended Audience :: Developers
Classifier: Topic :: Software Development :: Libraries
Classifier: Topic :: Software Development :: Embedded Systems
Classifier: Topic :: System :: Hardware
Classifier: License :: OSI Approved :: MIT License
Classifier: Programming Language :: Python :: 3
License-File: LICENSE
Requires-Dist: Adafruit-Blinka
Provides-Extra: optional
Dynamic: license-file
